CHANGELOG.rst
LICENSE
MANIFEST.in
README.rst
setup.py
mstax_sqlalchemy_filters.egg-info/PKG-INFO
mstax_sqlalchemy_filters.egg-info/SOURCES.txt
mstax_sqlalchemy_filters.egg-info/dependency_links.txt
mstax_sqlalchemy_filters.egg-info/requires.txt
mstax_sqlalchemy_filters.egg-info/top_level.txt
mstax_sqlalchemy_filters.egg-info/zip-safe
sqlalchemy_filters/__init__.py
sqlalchemy_filters/exceptions.py
sqlalchemy_filters/filters.py
sqlalchemy_filters/loads.py
sqlalchemy_filters/models.py
sqlalchemy_filters/pagination.py
sqlalchemy_filters/sorting.py