Metadata-Version: 2.1
Name: mstax-sqlalchemy-filters
Version: 1.0.0
Summary: A library to filter SQLAlchemy queries.
Home-page: https://github.com/juliotrigo/sqlalchemy-filters
Author: Student.com
Author-email: wearehiring@student.com
License: Apache License, Version 2.0
Platform: UNKNOWN
Classifier: Intended Audience :: Developers
Classifier: License :: OSI Approved :: Apache Software License
Classifier: Operating System :: OS Independent
Classifier: Programming Language :: Python
Classifier: Programming Language :: Python :: 3
Classifier: Programming Language :: Python :: 3.6
Classifier: Programming Language :: Python :: 3.7
Classifier: Programming Language :: Python :: 3.8
Classifier: Programming Language :: Python :: 3.9
Classifier: Programming Language :: Python :: 3.10
Classifier: Topic :: Database
Classifier: Topic :: Database :: Front-Ends
Classifier: Topic :: Software Development :: Libraries :: Python Modules
Provides-Extra: dev
Provides-Extra: mysql
Provides-Extra: postgresql
License-File: LICENSE
